{
	"credit": "By Snhnry",
	"textures": {
		"particle": "block/polished_granite",
		"wall": "block/polished_granite"
	},
	"elements": [
		{
			"from": [2, 0, 0],
			"to": [14, 4, 8],
			"faces": {
				"north": {"uv": [2, 12, 14, 16], "texture": "#wall", "cullface": "north"},
				"east": {"uv": [8, 12, 16, 16], "texture": "#wall"},
				"west": {"uv": [0, 12, 8, 16], "texture": "#wall"},
				"up": {"uv": [2, 0, 14, 8], "texture": "#wall", "cullface": "up"},
				"down": {"uv": [2, 8, 14, 16], "texture": "#wall", "cullface": "down"}
			}
		},
		{
			"from": [2, 11, 0],
			"to": [14, 16, 8],
			"rotation": {"angle": 0, "axis": "y", "origin": [8, 20, 8]},
			"faces": {
				"north": {"uv": [2, 0, 14, 5], "texture": "#wall", "cullface": "north"},
				"east": {"uv": [8, 0, 16, 5], "texture": "#wall"},
				"west": {"uv": [0, 0, 8, 5], "texture": "#wall"},
				"up": {"uv": [2, 0, 14, 8], "texture": "#wall", "cullface": "up"},
				"down": {"uv": [2, 8, 14, 16], "texture": "#wall", "cullface": "down"}
			}
		},
		{
			"from": [3, 4, 0],
			"to": [13, 12, 8],
			"rotation": {"angle": 0, "axis": "y", "origin": [8, 12, 8]},
			"faces": {
				"north": {"uv": [3, 4, 13, 12], "texture": "#wall", "cullface": "north"},
				"east": {"uv": [8, 4, 16, 12], "texture": "#wall"},
				"west": {"uv": [0, 4, 8, 12], "texture": "#wall"},
				"up": {"uv": [3, 0, 13, 8], "texture": "#wall", "cullface": "up"},
				"down": {"uv": [3, 8, 13, 16], "texture": "#wall", "cullface": "down"}
			}
		}
	]
}